ravegen/LICENSE
ravegen/__init__.py
ravegen/commands
ravegen/generateAp.py
ravegen/main.py
ravegen/rave_compl.bash
ravegen/ravegen
ravegen/version
ravegen/CloudEngine/__init__.py
ravegen/CloudEngine/cloudManager.py
ravegen/CloudEngine/gaeManager.py
ravegen/CloudEngine/herokuManager.py
ravegen/ConsoleEngine/__init__.py
ravegen/ConsoleEngine/consoleAPI.py
ravegen/ConsoleEngine/consoleManager.py
ravegen/ConsoleEngine/generateAutoCompletition.py
ravegen/Decorators/CallBackHandler.py
ravegen/Decorators/CommandHandler.py
ravegen/Decorators/Error.py
ravegen/Decorators/FunctionHandler.py
ravegen/Decorators/Handler.py
ravegen/Decorators/Image.py
ravegen/Decorators/MessageHandler.py
ravegen/Decorators/RaveGen.py
ravegen/Decorators/Text.py
ravegen/Decorators/__init__.py
ravegen/Decorators/functionManager.py
ravegen/Decorators/sadDec.py
ravegen/RaveEngine/__init__.py
ravegen/RaveEngine/botManager.py
ravegen/RaveEngine/configManager.py
ravegen/RaveEngine/gaeBotManager.py
ravegen/RaveEngine/herokuBotManager.py
ravegen/RaveEngine/projectManager.py
ravegen/Utils/__init__.py
ravegen/Utils/commandManager.py
ravegen/Utils/errorHandler.py
ravegen/Utils/inputManager.py
ravegen/Utils/logManager.py
ravegen/Utils/sad.py
ravegen/Utils/sadD.py
ravegen/Utils/utils.py
ravegen-0.3.1.data/scripts/ravegen
ravegen-0.3.1.dist-info/DESCRIPTION.rst
ravegen-0.3.1.dist-info/METADATA
ravegen-0.3.1.dist-info/RECORD
ravegen-0.3.1.dist-info/WHEEL
ravegen-0.3.1.dist-info/metadata.json
ravegen-0.3.1.dist-info/top_level.txt
tests/__init__.py
tests/test_botManager.py
tests/test_configManager.py
tests/test_inputManager.py
tests/test_logManager.py
tests/test_projectManager.py
tests/test_utils.py
