Metadata-Version: 2.0
Name: ravegen
Version: 0.3.1
Summary: Program for generate, create and deploy telegram bots readable way.
Home-page: https://github.com/ChrisChV/RaveGen-Telegram-bot-generator
Author: Christofer Chavez Carazas
Author-email: xnpiochv@gmail.com
License: MIT
Platform: UNKNOWN
Classifier: Programming Language :: Python :: 2.7
Classifier: License :: OSI Approved :: MIT License
Classifier: Operating System :: OS Independent
Requires-Dist: python-telegram-bot
